some_vhdl_problems/sr_flipflop/sr_flipflop.vhd
library IEEE;
use IEEE.STD_LOGIC_1164.ALL;

entity sr_flipflop is
    Port (
        clk : in  std_logic;
        S   : in  std_logic;
        R   : in  std_logic;
        Q   : out std_logic
    );
end sr_flipflop;

architecture Behavioral of sr_flipflop is
    signal q_reg : std_logic := '0';
begin

    process(clk)
    begin
        if rising_edge(clk) then
            if (S = '1' and R = '0') then
                q_reg <= '1';
            elsif (S = '0' and R = '1') then
                q_reg <= '0';
            elsif (S = '0' and R = '0') then
                q_reg <= q_reg;  -- hold state
            else
                q_reg <= 'X';    -- invalid S = R = 1
            end if;
        end if;
    end process;

    Q <= q_reg;

end Behavioral;

some_vhdl_problems/sr_flipflop/tb_sr_flipflop.vhd
library IEEE;
use IEEE.STD_LOGIC_1164.ALL;

entity tb_sr_flipflop is
end tb_sr_flipflop;

architecture Behavioral of tb_sr_flipflop is

    -- Testbench signals
    signal clk : std_logic := '0';
    signal S   : std_logic := '0';
    signal R   : std_logic := '0';
    signal Q   : std_logic;

    constant clk_period : time := 10 ns;

begin

    -- Direct entity instantiation (VHDL-2008 style)
    DUT : entity work.sr_flipflop
        port map (
            clk => clk,
            S   => S,
            R   => R,
            Q   => Q
        );

    -- Clock generation
    clk_process : process
    begin
        while true loop
            clk <= '0';
            wait for clk_period / 2;
            clk <= '1';
            wait for clk_period / 2;
        end loop;
    end process;

    -- Stimulus process
    stim_process : process
    begin
        -- Hold
        S <= '0'; R <= '0';
        wait for clk_period;

        -- Set
        S <= '1'; R <= '0';
        wait for clk_period;

        -- Hold
        S <= '0'; R <= '0';
        wait for clk_period;

        -- Reset
        S <= '0'; R <= '1';
        wait for clk_period;

        -- Hold
        S <= '0'; R <= '0';
        wait for clk_period;

        -- Invalid case
        S <= '1'; R <= '1';
        wait for clk_period;

        -- Back to hold
        S <= '0'; R <= '0';
        wait for clk_period;

        -- Stop simulation
        wait;
    end process;

end Behavioral;

some_vhdl_problems/sr_flipflop/wave.vcd
$date
  Mon Feb 02 13:22:11 2026
$end
$version
  GHDL v0
$end
$timescale
  1 fs
$end
$scope module standard $end
$upscope $end
$scope module std_logic_1164 $end
$upscope $end
$scope module tb_sr_flipflop $end
$var reg 1 ! clk $end
$var reg 1 " s $end
$var reg 1 # r $end
$var reg 1 $ q $end
$scope module dut $end
$var reg 1 % clk $end
$var reg 1 & s $end
$var reg 1 ' r $end
$var reg 1 ( q $end
$var reg 1 ) q_reg $end
$upscope $end
$upscope $end
$enddefinitions $end
#0
0!
0"
0#
0$
0%
0&
0'
0(
0)
#5000000
1!
1%
#10000000
0!
1"
0%
1&
#15000000
1!
1$
1%
1(
1)
#20000000
0!
0"
0%
0&
#25000000
1!
1%
#30000000
0!
1#
0%
1'
#35000000
1!
0$
1%
0(
0)
#40000000
0!
0#
0%
0'
#45000000
1!
1%
#50000000
0!
1"
1#
0%
1&
1'
#55000000
1!
X$
1%
X(
X)
#60000000
0!
0"
0#
0%
0&
0'
