full_subtractor/full_subtractor.vhd
library ieee;
use ieee.std_logic_1164.all;

entity full_subtractor is
    port(
        a,b,bin : in std_logic;
        d, bout : out std_logic
    );
end entity;

architecture beh of full_subtractor is
begin
    d <= (a xor b) xor bin;
    bout <= (bin and (not (a xor b))) or ((not a) and b);
end architecture;

full_subtractor/tb_full_subtractor.vhd
library ieee;
use ieee.std_logic_1164.all;

entity tb_full_subtractor is
end entity;

architecture sim of tb_full_subtractor is
  signal a, b, bin, d, bout : std_logic;
begin
  -- Instantiate the DUT
  uut: entity work.full_subtractor
    port map (
      a => a,
      b => b,
      bin => bin,
      d => d,
      bout => bout
    );

  -- Stimulus process
  process
  begin
    bin <= '0'; a <= '0'; b <= '0'; wait for 100 fs;
    bin <= '0'; a <= '0'; b <= '1'; wait for 100 fs;
    bin <= '0'; a <= '1'; b <= '0'; wait for 100 fs;
    bin <= '0'; a <= '1'; b <= '1'; wait for 100 fs;
    bin <= '1'; a <= '0'; b <= '0'; wait for 100 fs;
    bin <= '1'; a <= '0'; b <= '1'; wait for 100 fs;
    bin <= '1'; a <= '1'; b <= '0'; wait for 100 fs;
    bin <= '1'; a <= '1'; b <= '1'; wait for 100 fs;
    wait;  -- stop simulation
  end process;
end architecture;

full_subtractor/wave.vcd
$date
  Thu Dec 11 13:29:51 2025
$end
$version
  GHDL v0
$end
$timescale
  1 fs
$end
$scope module standard $end
$upscope $end
$scope module std_logic_1164 $end
$upscope $end
$scope module tb_full_subtractor $end
$var reg 1 ! a $end
$var reg 1 " b $end
$var reg 1 # bin $end
$var reg 1 $ d $end
$var reg 1 % bout $end
$scope module uut $end
$var reg 1 & a $end
$var reg 1 ' b $end
$var reg 1 ( bin $end
$var reg 1 ) d $end
$var reg 1 * bout $end
$upscope $end
$upscope $end
$enddefinitions $end
#0
0!
0"
0#
0$
0%
0&
0'
0(
0)
0*
#100
1"
1$
1%
1'
1)
1*
#200
1!
0"
0%
1&
0'
0*
#300
1"
0$
1'
0)
#400
0!
0"
1#
1$
1%
0&
0'
1(
1)
1*
#500
1"
0$
1'
0)
#600
1!
0"
0%
1&
0'
0*
#700
1"
1$
1%
1'
1)
1*
