moore_state/traffic.vhd
library IEEE;
use IEEE.STD_LOGIC_1164.ALL;
use IEEE.NUMERIC_STD.ALL;

entity traffic_light_moore is
    Port (
        clk    : in  STD_LOGIC;
        reset  : in  STD_LOGIC;
        red    : out STD_LOGIC;
        yellow : out STD_LOGIC;
        green  : out STD_LOGIC
    );
end traffic_light_moore;

architecture Behavioral of traffic_light_moore is

    -- State declaration
    type state_type is (RED_STATE, GREEN_STATE, YELLOW_STATE);
    signal current_state, next_state : state_type;

    -- Counter for timing
    signal count : integer range 0 to 5 := 0;

begin

    ------------------------------------------------------------------
    -- State register & counter
    ------------------------------------------------------------------
    process(clk)
    begin
        if rising_edge(clk) then
            if reset = '1' then
                current_state <= RED_STATE;
                count <= 0;
            else
                current_state <= next_state;

                if count = 5 then
                    count <= 0;
                else
                    count <= count + 1;
                end if;
            end if;
        end if;
    end process;

    ------------------------------------------------------------------
    -- Next state logic
    ------------------------------------------------------------------
    process(current_state, count)
    begin
        next_state <= current_state;

        case current_state is
            when RED_STATE =>
                if count = 5 then
                    next_state <= YELLOW_STATE;
                end if;

            when GREEN_STATE =>
                if count = 5 then
                    next_state <= RED_STATE;
                end if;

            when YELLOW_STATE =>
                if count = 5 then
                    next_state <= GREEN_STATE;
                end if;
        end case;
    end process;

    ------------------------------------------------------------------
    -- Output logic (Moore)
    ------------------------------------------------------------------
    process(current_state)
    begin
        -- Default OFF
        red    <= '0';
        yellow <= '0';
        green  <= '0';

        case current_state is
            when RED_STATE =>
                red <= '1';

            when GREEN_STATE =>
                green <= '1';

            when YELLOW_STATE =>
                yellow <= '1';
        end case;
    end process;

end Behavioral;

moore_state/tb_traffic.vhd
library IEEE;
use IEEE.STD_LOGIC_1164.ALL;

entity tb_traffic is
end tb_traffic;

architecture Behavioral of tb_traffic is

    -- Component declaration
    component traffic_light_moore
        Port (
            clk    : in  STD_LOGIC;
            reset  : in  STD_LOGIC;
            red    : out STD_LOGIC;
            yellow : out STD_LOGIC;
            green  : out STD_LOGIC
        );
    end component;

    -- Testbench signals
    signal clk    : STD_LOGIC := '0';
    signal reset  : STD_LOGIC := '0';
    signal red    : STD_LOGIC;
    signal yellow : STD_LOGIC;
    signal green  : STD_LOGIC;

    constant clk_period : time := 10 ns;

begin

    ------------------------------------------------------------------
    -- Instantiate the Unit Under Test (UUT)
    ------------------------------------------------------------------
    uut: traffic_light_moore
        port map (
            clk    => clk,
            reset  => reset,
            red    => red,
            yellow => yellow,
            green  => green
        );

    ------------------------------------------------------------------
    -- Clock generation
    ------------------------------------------------------------------
    clk_process : process
    begin
        while true loop
            clk <= '0';
            wait for clk_period / 2;
            clk <= '1';
            wait for clk_period / 2;
        end loop;
    end process;

    ------------------------------------------------------------------
    -- Stimulus process
    ------------------------------------------------------------------
    stim_proc: process
    begin
        -- Apply reset
        reset <= '1';
        wait for 20 ns;
        reset <= '0';

        -- Run simulation long enough to see all states
        wait for 400 ns;

        -- End simulation
        wait;
    end process;

end Behavioral;

moore_state/wave.vcd
$date
  Wed Jan 14 11:13:08 2026
$end
$version
  GHDL v0
$end
$timescale
  1 fs
$end
$scope module standard $end
$upscope $end
$scope module std_logic_1164 $end
$upscope $end
$scope module numeric_std $end
$upscope $end
$scope module tb_traffic $end
$var reg 1 ! clk $end
$var reg 1 " reset $end
$var reg 1 # red $end
$var reg 1 $ yellow $end
$var reg 1 % green $end
$scope module uut $end
$var reg 1 & clk $end
$var reg 1 ' reset $end
$var reg 1 ( red $end
$var reg 1 ) yellow $end
$var reg 1 * green $end
$comment current_state is not handled $end
$comment next_state is not handled $end
$var integer 32 + count $end
$upscope $end
$upscope $end
$enddefinitions $end
#0
0!
1"
1#
0$
0%
0&
1'
1(
0)
0*
b0 +
#5000000
1!
1&
#10000000
0!
0&
#15000000
1!
1&
#20000000
0!
0"
0&
0'
#25000000
1!
1&
b1 +
#30000000
0!
0&
#35000000
1!
1&
b10 +
#40000000
0!
0&
#45000000
1!
1&
b11 +
#50000000
0!
0&
#55000000
1!
1&
b100 +
#60000000
0!
0&
#65000000
1!
1&
b101 +
#70000000
0!
0&
#75000000
1!
0#
1$
1&
0(
1)
b0 +
#80000000
0!
0&
#85000000
1!
1&
b1 +
#90000000
0!
0&
#95000000
1!
1&
b10 +
#100000000
0!
0&
#105000000
1!
1&
b11 +
#110000000
0!
0&
#115000000
1!
1&
b100 +
#120000000
0!
0&
#125000000
1!
1&
b101 +
#130000000
0!
0&
#135000000
1!
0$
1%
1&
0)
1*
b0 +
#140000000
0!
0&
#145000000
1!
1&
b1 +
#150000000
0!
0&
#155000000
1!
1&
b10 +
#160000000
0!
0&
#165000000
1!
1&
b11 +
#170000000
0!
0&
#175000000
1!
1&
b100 +
#180000000
0!
0&
#185000000
1!
1&
b101 +
#190000000
0!
0&
#195000000
1!
1#
0%
1&
1(
0*
b0 +
#200000000
0!
0&
#205000000
1!
1&
b1 +
#210000000
0!
0&
#215000000
1!
1&
b10 +
#220000000
0!
0&
#225000000
1!
1&
b11 +
#230000000
0!
0&
#235000000
1!
1&
b100 +
#240000000
0!
0&
#245000000
1!
1&
b101 +
#250000000
0!
0&
#255000000
1!
0#
1$
1&
0(
1)
b0 +
#260000000
0!
0&
#265000000
1!
1&
b1 +
#270000000
0!
0&
#275000000
1!
1&
b10 +
#280000000
0!
0&
#285000000
1!
1&
b11 +
#290000000
0!
0&
#295000000
1!
1&
b100 +
#300000000
0!
0&
#305000000
1!
1&
b101 +
#310000000
0!
0&
#315000000
1!
0$
1%
1&
0)
1*
b0 +
#320000000
0!
0&
#325000000
1!
1&
b1 +
#330000000
0!
0&
#335000000
1!
1&
b10 +
#340000000
0!
0&
#345000000
1!
1&
b11 +
#350000000
0!
0&
#355000000
1!
1&
b100 +
#360000000
0!
0&
#365000000
1!
1&
b101 +
#370000000
0!
0&
#375000000
1!
1#
0%
1&
1(
0*
b0 +
#380000000
0!
0&
#385000000
1!
1&
b1 +
#390000000
0!
0&
#395000000
1!
1&
b10 +
#400000000
0!
0&
#405000000
1!
1&
b11 +
#410000000
0!
0&
#415000000
1!
1&
b100 +
#420000000
0!
0&
#425000000
1!
1&
b101 +
#430000000
0!
0&
#435000000
1!
0#
1$
1&
0(
1)
b0 +
#440000000
0!
0&
#445000000
1!
1&
b1 +
#450000000
0!
0&
#455000000
1!
1&
b10 +
#460000000
0!
0&
#465000000
1!
1&
b11 +
#470000000
0!
0&
#475000000
1!
1&
b100 +
#480000000
0!
0&
#485000000
1!
1&
b101 +
#490000000
0!
0&
#495000000
1!
0$
1%
1&
0)
1*
b0 +
