some_vhdl_problems/binary_to_bcd/binary_to_bcd.vhd
library IEEE;
use IEEE.STD_LOGIC_1164.ALL;
use IEEE.NUMERIC_STD.ALL;

entity bin_to_bcd is
    Port (
        bin : in  STD_LOGIC_VECTOR(7 downto 0);
        bcd : out STD_LOGIC_VECTOR(11 downto 0)
    );
end bin_to_bcd;

architecture Behavioral of bin_to_bcd is

    signal uval      : unsigned(7 downto 0);

    -- Intermediate wide results
    signal h_tmp     : unsigned(7 downto 0);
    signal t_tmp     : unsigned(7 downto 0);
    signal o_tmp     : unsigned(7 downto 0);

    -- Final BCD digits
    signal hundreds  : unsigned(3 downto 0);
    signal tens      : unsigned(3 downto 0);
    signal ones      : unsigned(3 downto 0);

begin

    uval <= unsigned(bin);

    -- Full-width division results
    h_tmp <= uval / 100;
    t_tmp <= (uval / 10) mod 10;
    o_tmp <= uval mod 10;

    -- Safe narrowing (values are guaranteed 0–9)
    hundreds <= h_tmp(3 downto 0);
    tens     <= t_tmp(3 downto 0);
    ones     <= o_tmp(3 downto 0);

    bcd(11 downto 8) <= std_logic_vector(hundreds);
    bcd(7 downto 4)  <= std_logic_vector(tens);
    bcd(3 downto 0)  <= std_logic_vector(ones);

end Behavioral;

some_vhdl_problems/binary_to_bcd/tb_binary_to_bcd.vhd
library IEEE;
use IEEE.STD_LOGIC_1164.ALL;
use IEEE.NUMERIC_STD.ALL;

entity tb_binary_to_bcd is
end tb_binary_to_bcd;

architecture Behavioral of tb_binary_to_bcd is

    -- DUT signals
    signal bin : STD_LOGIC_VECTOR(7 downto 0);
    signal bcd : STD_LOGIC_VECTOR(11 downto 0);

begin

    -- ===============================
    -- DUT instantiation (NO component)
    -- ===============================
    DUT : entity work.bin_to_bcd
        port map (
            bin => bin,
            bcd => bcd
        );

    -- ===============================
    -- Stimulus process
    -- ===============================
    stim_proc : process
    begin

        -- 0
        bin <= "00000000";
        wait for 10 ns;

        -- 1
        bin <= "00000001";
        wait for 10 ns;

        -- 9
        bin <= "00001001";
        wait for 10 ns;

        -- 10
        bin <= "00001010";
        wait for 10 ns;

        -- 42
        bin <= "00101010";
        wait for 10 ns;

        -- 99
        bin <= "01100011";
        wait for 10 ns;

        -- 100
        bin <= "01100100";
        wait for 10 ns;

        -- 128
        bin <= "10000000";
        wait for 10 ns;

        -- 200
        bin <= "11001000";
        wait for 10 ns;

        -- 255
        bin <= "11111111";
        wait for 10 ns;

        wait;
    end process;


end Behavioral;

some_vhdl_problems/binary_to_bcd/wave.vcd
$date
  Mon Feb 02 20:05:16 2026
$end
$version
  GHDL v0
$end
$timescale
  1 fs
$end
$scope module standard $end
$upscope $end
$scope module std_logic_1164 $end
$upscope $end
$scope module numeric_std $end
$upscope $end
$scope module tb_binary_to_bcd $end
$var reg 8 ! bin[7:0] $end
$var reg 12 " bcd[11:0] $end
$scope module dut $end
$var reg 8 # bin[7:0] $end
$var reg 12 $ bcd[11:0] $end
$var reg 8 % uval[7:0] $end
$var reg 8 & h_tmp[7:0] $end
$var reg 8 ' t_tmp[7:0] $end
$var reg 8 ( o_tmp[7:0] $end
$var reg 4 ) hundreds[3:0] $end
$var reg 4 * tens[3:0] $end
$var reg 4 + ones[3:0] $end
$upscope $end
$upscope $end
$enddefinitions $end
#0
b00000000 !
b000000000000 "
b00000000 #
b000000000000 $
b00000000 %
b00000000 &
b00000000 '
b00000000 (
b0000 )
b0000 *
b0000 +
#10000000
b00000001 !
b000000000001 "
b00000001 #
b000000000001 $
b00000001 %
b00000001 (
b0001 +
#20000000
b00001001 !
b000000001001 "
b00001001 #
b000000001001 $
b00001001 %
b00001001 (
b1001 +
#30000000
b00001010 !
b000000010000 "
b00001010 #
b000000010000 $
b00001010 %
b00000001 '
b00000000 (
b0001 *
b0000 +
#40000000
b00101010 !
b000001000010 "
b00101010 #
b000001000010 $
b00101010 %
b00000100 '
b00000010 (
b0100 *
b0010 +
#50000000
b01100011 !
b000010011001 "
b01100011 #
b000010011001 $
b01100011 %
b00001001 '
b00001001 (
b1001 *
b1001 +
#60000000
b01100100 !
b000100000000 "
b01100100 #
b000100000000 $
b01100100 %
b00000001 &
b00000000 '
b00000000 (
b0001 )
b0000 *
b0000 +
#70000000
b10000000 !
b000100101000 "
b10000000 #
b000100101000 $
b10000000 %
b00000010 '
b00001000 (
b0010 *
b1000 +
#80000000
b11001000 !
b001000000000 "
b11001000 #
b001000000000 $
b11001000 %
b00000010 &
b00000000 '
b00000000 (
b0010 )
b0000 *
b0000 +
#90000000
b11111111 !
b001001010101 "
b11111111 #
b001001010101 $
b11111111 %
b00000101 '
b00000101 (
b0101 *
b0101 +
