demux_1x8/demux_1x8.vhd
library ieee;
use ieee.std_logic_1164.all;

entity demux_1x8 is
    port(
        i : in std_logic;
        s : in std_logic_vector(2 downto 0);
        y : out std_logic_vector(7 downto 0)
    );
    end entity;

architecture beh of demux_1x8 is
begin
    process(i, s)
    begin
        y <= (others => '0');
        case s is
            when "000" => y(0) <= i;
            when "001" => y(1) <= i;
            when "010" => y(2) <= i;
            when "011" => y(3) <= i;
            when "100" => y(4) <= i;
            when "101" => y(5) <= i;
            when "110" => y(6) <= i;
            when "111" => y(7) <= i;
            when others => y <= (others => '0');
        end case;
    end process;

end architecture;

demux_1x8/tb_demux_1x8.vhd
library ieee;
use ieee.std_logic_1164.all;

entity tb_demux_1x8 is
end entity;

architecture sil of tb_demux_1x8 is
    signal i : std_logic;
    signal s : std_logic_vector(2 downto 0) := (others => '0'); -- other part assigns 0 to the bits
    signal y : std_logic_vector(7 downto 0);

begin
    uut: entity work.demux_1x8
        port map (
            i => i,
            s => s,
            y => y
        );

    process
    begin
        i <= '1';  -- Example data

        s <= "000"; wait for 50 fs;
        s <= "001"; wait for 50 fs;
        s <= "010"; wait for 50 fs;
        s <= "011"; wait for 50 fs;
        s <= "100"; wait for 50 fs;
        s <= "101"; wait for 50 fs;
        s <= "110"; wait for 50 fs;
        s <= "111"; wait for 50 fs;
        wait;
    end process;
end architecture;

demux_1x8/wave.vcd
$date
  Thu Nov 27 13:30:31 2025
$end
$version
  GHDL v0
$end
$timescale
  1 fs
$end
$scope module standard $end
$upscope $end
$scope module std_logic_1164 $end
$upscope $end
$scope module tb_demux_1x8 $end
$var reg 1 ! i $end
$var reg 3 " s[2:0] $end
$var reg 8 # y[7:0] $end
$scope module uut $end
$var reg 1 $ i $end
$var reg 3 % s[2:0] $end
$var reg 8 & y[7:0] $end
$upscope $end
$upscope $end
$enddefinitions $end
#0
1!
b000 "
b00000001 #
1$
b000 %
b00000001 &
#50
b001 "
b00000010 #
b001 %
b00000010 &
#100
b010 "
b00000100 #
b010 %
b00000100 &
#150
b011 "
b00001000 #
b011 %
b00001000 &
#200
b100 "
b00010000 #
b100 %
b00010000 &
#250
b101 "
b00100000 #
b101 %
b00100000 &
#300
b110 "
b01000000 #
b110 %
b01000000 &
#350
b111 "
b10000000 #
b111 %
b10000000 &
