some_vhdl_problems/octal_to_binary_encoder/octal_to_binary_encoder.vhd
library IEEE;
use IEEE.STD_LOGIC_1164.ALL;

entity octal_to_binary_encoder is
    Port (
        D : in  STD_LOGIC_VECTOR(7 downto 0); -- Octal inputs
        B : out STD_LOGIC_VECTOR(2 downto 0)  -- Binary output
    );
end octal_to_binary_encoder;

architecture Behavioral of octal_to_binary_encoder is
begin
    process(D)
    begin
        case D is
            when "00000001" => B <= "000"; -- D0
            when "00000010" => B <= "001"; -- D1
            when "00000100" => B <= "010"; -- D2
            when "00001000" => B <= "011"; -- D3
            when "00010000" => B <= "100"; -- D4
            when "00100000" => B <= "101"; -- D5
            when "01000000" => B <= "110"; -- D6
            when "10000000" => B <= "111"; -- D7
            when others     => B <= "000"; -- Invalid / no input
        end case;
    end process;
end Behavioral;

some_vhdl_problems/octal_to_binary_encoder/tb_octal_to_binary_encoder.vhd
library IEEE;
use IEEE.STD_LOGIC_1164.ALL;

entity tb_octal_to_binary_encoder is
end tb_octal_to_binary_encoder;

architecture Behavioral of tb_octal_to_binary_encoder is

    -- Testbench signals
    signal D_tb : STD_LOGIC_VECTOR(7 downto 0) := (others => '0');
    signal B_tb : STD_LOGIC_VECTOR(2 downto 0);

begin

    -- Direct entity instantiation (no component)
    DUT : entity work.octal_to_binary_encoder
        port map (
            D => D_tb,
            B => B_tb
        );

    -- Stimulus process
    stim_proc : process
    begin
        D_tb <= "00000001"; wait for 10 ns; -- 0
        D_tb <= "00000010"; wait for 10 ns; -- 1
        D_tb <= "00000100"; wait for 10 ns; -- 2
        D_tb <= "00001000"; wait for 10 ns; -- 3
        D_tb <= "00010000"; wait for 10 ns; -- 4
        D_tb <= "00100000"; wait for 10 ns; -- 5
        D_tb <= "01000000"; wait for 10 ns; -- 6
        D_tb <= "10000000"; wait for 10 ns; -- 7

        -- Invalid / idle case
        D_tb <= "00000000"; wait for 10 ns;

        wait; -- stop simulation
    end process;

end Behavioral;

some_vhdl_problems/octal_to_binary_encoder/wave.vcd
$date
  Thu Jan 29 21:23:48 2026
$end
$version
  GHDL v0
$end
$timescale
  1 fs
$end
$scope module standard $end
$upscope $end
$scope module std_logic_1164 $end
$upscope $end
$scope module tb_octal_to_binary_encoder $end
$var reg 8 ! d_tb[7:0] $end
$var reg 3 " b_tb[2:0] $end
$scope module dut $end
$var reg 8 # d[7:0] $end
$var reg 3 $ b[2:0] $end
$upscope $end
$upscope $end
$enddefinitions $end
#0
b00000001 !
b000 "
b00000001 #
b000 $
#10000000
b00000010 !
b001 "
b00000010 #
b001 $
#20000000
b00000100 !
b010 "
b00000100 #
b010 $
#30000000
b00001000 !
b011 "
b00001000 #
b011 $
#40000000
b00010000 !
b100 "
b00010000 #
b100 $
#50000000
b00100000 !
b101 "
b00100000 #
b101 $
#60000000
b01000000 !
b110 "
b01000000 #
b110 $
#70000000
b10000000 !
b111 "
b10000000 #
b111 $
#80000000
b00000000 !
b000 "
b00000000 #
b000 $
