mux_8x1/mux_8x1.vhd
library ieee;
use ieee.std_logic_1164.all;

entity mux_8x1 is
    port(
        i : in std_logic_vector(7 downto 0); --0 to 7 position of bits so 8-bits
        s : in std_logic_vector(2 downto 0); --0 to 2 position of bits so 3-bits
        y : out std_logic
    );
    end entity;

architecture beh of mux_8x1 is
begin
    with s select
        y <= i(0) when "000",
            i(1) when "001",
            i(2) when "010",
            i(3) when "011",
            i(4) when "100",
            i(5) when "101",
            i(6) when "110",
            i(7) when "111",
            '0' when others;
end architecture;

-- other way
-- architecture Behavioral of mux_8x1 is
-- begin
--     process(I, S)
--     begin
--         case S is
--             when "000" => Y <= I(0);
--             when "001" => Y <= I(1);
--             when "010" => Y <= I(2);
--             when "011" => Y <= I(3);
--             when "100" => Y <= I(4);
--             when "101" => Y <= I(5);
--             when "110" => Y <= I(6);
--             when "111" => Y <= I(7);
--             when others => Y <= '0';
--         end case;
--     end process;
-- end Behavioral;

mux_8x1/tb_mux_8x1.vhd
library ieee;
use ieee.std_logic_1164.all;

entity tb_mux_8x1 is
end entity;

architecture sil of tb_mux_8x1 is
    signal i : std_logic_vector(7 downto 0) := (others => '0'); -- other part assigns 0 to the bits
    signal s : std_logic_vector(2 downto 0) := (others => '0'); -- other part assigns 0 to the bits
    signal y : std_logic;

begin
    uut: entity work.mux_8x1
        port map (
            i => i,
            s => s,
            y => y
        );
    
    process
    begin
        i <= "00110101";  -- Example data

        s <= "000"; wait for 50 fs;
        s <= "001"; wait for 50 fs;
        s <= "010"; wait for 50 fs;
        s <= "011"; wait for 50 fs;
        s <= "100"; wait for 50 fs;
        s <= "101"; wait for 50 fs;
        s <= "110"; wait for 50 fs;
        s <= "111"; wait for 50 fs;
        wait;
    end process;
end architecture;

-- while testing in gtkwave, 000 will select i(0) so the first selected value will be 1 so the result of the test will be "10101100"

mux_8x1/wave.vcd
$date
  Thu Nov 27 08:19:52 2025
$end
$version
  GHDL v0
$end
$timescale
  1 fs
$end
$scope module standard $end
$upscope $end
$scope module std_logic_1164 $end
$upscope $end
$scope module tb_mux_8x1 $end
$var reg 8 ! i[7:0] $end
$var reg 3 " s[2:0] $end
$var reg 1 # y $end
$scope module uut $end
$var reg 8 $ i[7:0] $end
$var reg 3 % s[2:0] $end
$var reg 1 & y $end
$upscope $end
$upscope $end
$enddefinitions $end
#0
b00110101 !
b000 "
1#
b00110101 $
b000 %
1&
#50
b001 "
0#
b001 %
0&
#100
b010 "
1#
b010 %
1&
#150
b011 "
0#
b011 %
0&
#200
b100 "
1#
b100 %
1&
#250
b101 "
b101 %
#300
b110 "
0#
b110 %
0&
#350
b111 "
b111 %
