decade_counter/decade_counter.vhd
library ieee;
use ieee.std_logic_1164.all;
use ieee.numeric_std.all;

entity decade_counter is
    port(
        clk   : in  std_logic;
        count : out std_logic_vector(3 downto 0)
    );
end entity;

architecture beh of decade_counter is
    signal cnt : unsigned(3 downto 0) := (others => '0');
begin
    process(clk)
    begin
        if rising_edge(clk) then
            if cnt = 9 then
                cnt <= (others => '0');  -- reset to 0 after 9
            else
                cnt <= cnt + 1;
            end if;
        end if;
    end process;

    count <= std_logic_vector(cnt);
end architecture;

decade_counter/tb_decade_counter.vhd
library ieee;
use ieee.std_logic_1164.all;

entity tb_decade_counter is
end entity;

architecture beh of tb_decade_counter is
    signal clk   : std_logic;
    signal count : std_logic_vector(3 downto 0);
    constant clk_period : time := 10 ns;
begin
    uut: entity work.decade_counter
        port map(
            clk   => clk,
            count => count
        );

    process
    begin
        while true loop
            clk <= '0';
            wait for clk_period;
            clk <= '1';
            wait for clk_period;
        end loop;
    end process;

    process
    begin
        wait for 200 ns;
        wait;
    end process;
end architecture;

decade_counter/wave.vcd
$date
  Sat Dec 27 21:28:07 2025
$end
$version
  GHDL v0
$end
$timescale
  1 fs
$end
$scope module standard $end
$upscope $end
$scope module std_logic_1164 $end
$upscope $end
$scope module numeric_std $end
$upscope $end
$scope module tb_decade_counter $end
$var reg 1 ! clk $end
$var reg 4 " count[3:0] $end
$scope module uut $end
$var reg 1 # clk $end
$var reg 4 $ count[3:0] $end
$var reg 4 % cnt[3:0] $end
$upscope $end
$upscope $end
$enddefinitions $end
#0
0!
b0000 "
0#
b0000 $
b0000 %
#10000000
1!
b0001 "
1#
b0001 $
b0001 %
#20000000
0!
0#
#30000000
1!
b0010 "
1#
b0010 $
b0010 %
#40000000
0!
0#
#50000000
1!
b0011 "
1#
b0011 $
b0011 %
#60000000
0!
0#
#70000000
1!
b0100 "
1#
b0100 $
b0100 %
#80000000
0!
0#
#90000000
1!
b0101 "
1#
b0101 $
b0101 %
#100000000
0!
0#
#110000000
1!
b0110 "
1#
b0110 $
b0110 %
#120000000
0!
0#
#130000000
1!
b0111 "
1#
b0111 $
b0111 %
#140000000
0!
0#
#150000000
1!
b1000 "
1#
b1000 $
b1000 %
#160000000
0!
0#
#170000000
1!
b1001 "
1#
b1001 $
b1001 %
#180000000
0!
0#
#190000000
1!
b0000 "
1#
b0000 $
b0000 %
