melay_state/sequence_detection.vhd
library IEEE;
use IEEE.STD_LOGIC_1164.ALL;

entity seq_1011_mealy is
    Port (
        clk   : in  STD_LOGIC;
        reset : in  STD_LOGIC;
        x     : in  STD_LOGIC;  -- serial input
        z     : out STD_LOGIC   -- output = 1 when 1011 detected
    );
end seq_1011_mealy;

architecture Behavioral of seq_1011_mealy is

    type state_type is (S0, S1, S2, S3);
    signal current_state, next_state : state_type;

begin

    ------------------------------------------------------------------
    -- State register
    ------------------------------------------------------------------
    process(clk)
    begin
        if falling_edge(clk) then
            if reset = '1' then
                current_state <= S0;
            else
                current_state <= next_state;
            end if;
        end if;
    end process;

    ------------------------------------------------------------------
    -- Next state and output logic (Mealy)
    ------------------------------------------------------------------
    process(current_state, x)
    begin
        -- Default assignments
        next_state <= current_state;
        z <= '0';

        case current_state is

            when S0 =>
                if x = '1' then
                    next_state <= S1;
                else
                    next_state <= S0;
                end if;

            when S1 =>  -- "1"
                if x = '0' then
                    next_state <= S2;
                else
                    next_state <= S1; -- stay for overlapping
                end if;

            when S2 =>  -- "10"
                if x = '1' then
                    next_state <= S3;
                else
                    next_state <= S0;
                end if;

            when S3 =>  -- "101"
                if x = '1' then
                    z <= '1';         -- 1011 detected
                    next_state <= S1; -- overlap handling
                else
                    next_state <= S2; -- 1010 → "10"
                end if;

        end case;
    end process;

end Behavioral;

melay_state/tb_sequence_detector.vhd
library IEEE;
use IEEE.STD_LOGIC_1164.ALL;

entity tb_seq_1011_mealy is
end tb_seq_1011_mealy;

architecture Behavioral of tb_seq_1011_mealy is

    -- Component declaration
    component seq_1011_mealy
        Port (
            clk   : in  STD_LOGIC;
            reset : in  STD_LOGIC;
            x     : in  STD_LOGIC;
            z     : out STD_LOGIC
        );
    end component;

    -- Signals
    signal clk   : STD_LOGIC := '0';
    signal reset : STD_LOGIC := '0';
    signal x     : STD_LOGIC := '0';
    signal z     : STD_LOGIC;

    constant clk_period : time := 10 ns;

begin

    ------------------------------------------------------------------
    -- Instantiate Unit Under Test (UUT)
    ------------------------------------------------------------------
    uut: seq_1011_mealy
        port map (
            clk   => clk,
            reset => reset,
            x     => x,
            z     => z
        );

    ------------------------------------------------------------------
    -- Clock generation
    ------------------------------------------------------------------
    clk_process : process
    begin
        while true loop
            clk <= '0';
            wait for clk_period / 2;
            clk <= '1';
            wait for clk_period / 2;
        end loop;
    end process;

    ------------------------------------------------------------------
    -- Stimulus process
    ------------------------------------------------------------------
    stim_proc : process
    begin
        -- Apply reset
        -- reset <= '1';
        -- wait for 20 ns;
        -- reset <= '0';

        -- Input sequence: 1 0 1 1 0 1 0 1 1
        -- Expected z:      0 0 0 1 0 0 0 0 1

        x <= '1'; wait for clk_period;
        x <= '0'; wait for clk_period;

        x <= '1'; wait for clk_period;
        x <= '1'; wait for clk_period; -- z = 1 (1011)

        x <= '0'; wait for clk_period;
        x <= '1'; wait for clk_period;
        x <= '0'; wait for clk_period;
        x <= '1'; wait for clk_period;
        x <= '1'; wait for clk_period; -- z = 1 (overlapping)

        -- End simulation
        wait;
    end process;

end Behavioral;

melay_state/wave.vcd
$date
  Wed Jan 14 11:48:55 2026
$end
$version
  GHDL v0
$end
$timescale
  1 fs
$end
$scope module standard $end
$upscope $end
$scope module std_logic_1164 $end
$upscope $end
$scope module tb_seq_1011_mealy $end
$var reg 1 ! clk $end
$var reg 1 " reset $end
$var reg 1 # x $end
$var reg 1 $ z $end
$scope module uut $end
$var reg 1 % clk $end
$var reg 1 & reset $end
$var reg 1 ' x $end
$var reg 1 ( z $end
$comment current_state is not handled $end
$comment next_state is not handled $end
$upscope $end
$upscope $end
$enddefinitions $end
#0
0!
0"
1#
0$
0%
0&
1'
0(
#5000000
1!
1%
#10000000
0!
0#
0%
0'
#15000000
1!
1%
#20000000
0!
1#
0%
1'
#25000000
1!
1%
#30000000
0!
1$
0%
1(
#35000000
1!
1%
#40000000
0!
0#
0$
0%
0'
0(
#45000000
1!
1%
#50000000
0!
1#
0%
1'
#55000000
1!
1%
#60000000
0!
0#
0%
0'
#65000000
1!
1%
#70000000
0!
1#
0$
0%
1'
0(
#75000000
1!
1%
#80000000
0!
1$
0%
1(
#85000000
1!
1%
#90000000
0!
0$
0%
0(
