some_vhdl_problems/shift_register/shift_register.vhd
library IEEE;
use IEEE.STD_LOGIC_1164.ALL;

entity shift_register_4bit is
    Port (
        clk        : in  std_logic;
        reset      : in  std_logic;
        serial_in  : in  std_logic;
        serial_out : out std_logic
    );
end shift_register_4bit;

architecture Behavioral of shift_register_4bit is
    signal reg : std_logic_vector(3 downto 0);
begin

    process(clk)
    begin
        if rising_edge(clk) then
            if reset = '1' then
                reg <= (others => '0');
            else
                reg <= serial_in & reg(3 downto 1); -- & operation in vhdl is for concatination
            end if;
        end if;
    end process;

    serial_out <= reg(0);

end Behavioral;

some_vhdl_problems/shift_register/tb_shift_register.vhd
library IEEE;
use IEEE.STD_LOGIC_1164.ALL;

entity tb_shift_register is
end tb_shift_register;

architecture Behavioral of tb_shift_register is

    -- Testbench signals
    signal clk        : std_logic := '0';
    signal reset      : std_logic := '0';
    signal serial_in  : std_logic := '0';
    signal serial_out : std_logic;

    constant clk_period : time := 10 ns;

begin

    -- Direct entity instantiation (NO component)
    DUT : entity work.shift_register_4bit
        port map (
            clk        => clk,
            reset      => reset,
            serial_in  => serial_in,
            serial_out => serial_out
        );

    -- Clock generation
    clk_process : process
    begin
        while true loop
            clk <= '0';
            wait for clk_period / 2;
            clk <= '1';
            wait for clk_period / 2;
        end loop;
    end process;

    -- Stimulus process
    stim_process : process
    begin
        -- Apply reset
        reset <= '1';
        wait for clk_period;
        reset <= '0';

        -- Shift in serial data: 1 0 1 1
        serial_in <= '1';
        wait for clk_period;

        serial_in <= '0';
        wait for clk_period;

        serial_in <= '1';
        wait for clk_period;

        serial_in <= '1';
        wait for clk_period;

        -- Extra clocks to observe serial_out
        serial_in <= '0';
        wait for 4 * clk_period;

        -- End simulation
        wait;
    end process;

end Behavioral;

some_vhdl_problems/shift_register/wave.vcd
$date
  Thu Jan 29 18:40:58 2026
$end
$version
  GHDL v0
$end
$timescale
  1 fs
$end
$scope module standard $end
$upscope $end
$scope module std_logic_1164 $end
$upscope $end
$scope module tb_shift_register $end
$var reg 1 ! clk $end
$var reg 1 " reset $end
$var reg 1 # serial_in $end
$var reg 1 $ serial_out $end
$scope module dut $end
$var reg 1 % clk $end
$var reg 1 & reset $end
$var reg 1 ' serial_in $end
$var reg 1 ( serial_out $end
$var reg 4 ) reg[3:0] $end
$upscope $end
$upscope $end
$enddefinitions $end
#0
0!
1"
0#
U$
0%
1&
0'
U(
bUUUU )
#5000000
1!
0$
1%
0(
b0000 )
#10000000
0!
0"
1#
0%
0&
1'
#15000000
1!
1%
b1000 )
#20000000
0!
0#
0%
0'
#25000000
1!
1%
b0100 )
#30000000
0!
1#
0%
1'
#35000000
1!
1%
b1010 )
#40000000
0!
0%
#45000000
1!
1$
1%
1(
b1101 )
#50000000
0!
0#
0%
0'
#55000000
1!
0$
1%
0(
b0110 )
#60000000
0!
0%
#65000000
1!
1$
1%
1(
b0011 )
#70000000
0!
0%
#75000000
1!
1%
b0001 )
#80000000
0!
0%
#85000000
1!
0$
1%
0(
b0000 )
