t_flipflop/t_flipflop.vhd
library ieee;
use ieee.std_logic_1164.all;

entity t_flipflop is
    port(
        clk : in std_logic;
        d : in std_logic;
        q : out std_logic
    );
end entity;

architecture beh of t_flipflop is
begin
    process(clk)
    begin
        if rising_edge(clk) then
            q<= not d;
        end if;
    end process;
end architecture;

t_flipflop/tb_t_flipflop.vhd
library ieee;
use ieee.std_logic_1164.all;

entity tb_t_flipflop is
end entity;

architecture beh of tb_t_flipflop is
    signal d, clk, q : std_logic;
    constant clk_period :time := 10 ns;
begin
    uut: entity work.t_flipflop
        port map(
            d => d,
            clk => clk,
            q => q
        );
    
    process
    begin
        while true loop
            clk <= '0';
            wait for clk_period;
            clk <= '1';
            wait for clk_period;
        end loop;
    end process;

    process
    begin
        d <= '0'; wait for 20 ns;
        d <='1'; wait for 20 ns;
        d <='0'; wait for 20 ns;
        d <='1'; wait for 20 ns;
        wait;
    end process;
end architecture;

t_flipflop/wave.vcd
$date
  Sun Dec 14 11:09:34 2025
$end
$version
  GHDL v0
$end
$timescale
  1 fs
$end
$scope module standard $end
$upscope $end
$scope module std_logic_1164 $end
$upscope $end
$scope module tb_t_flipflop $end
$var reg 1 ! d $end
$var reg 1 " clk $end
$var reg 1 # q $end
$scope module uut $end
$var reg 1 $ clk $end
$var reg 1 % d $end
$var reg 1 & q $end
$upscope $end
$upscope $end
$enddefinitions $end
#0
0!
0"
U#
0$
0%
U&
#10000000
1"
1#
1$
1&
#20000000
1!
0"
0$
1%
#30000000
1"
0#
1$
0&
#40000000
0!
0"
0$
0%
#50000000
1"
1#
1$
1&
#60000000
1!
0"
0$
1%
#70000000
1"
0#
1$
0&
