some_vhdl_problems/structural_3bit_comparator/comparator_3bit.vhd
library IEEE;
use IEEE.STD_LOGIC_1164.ALL;

entity comparator_3bit is
    Port (
        A  : in  STD_LOGIC_VECTOR(2 downto 0);
        B  : in  STD_LOGIC_VECTOR(2 downto 0);
        GT : out STD_LOGIC;
        EQ : out STD_LOGIC;
        LT : out STD_LOGIC
    );
end comparator_3bit;

architecture structural of comparator_3bit is

    -- Internal signals
    signal nB0, nB1, nB2 : STD_LOGIC;
    signal nA0, nA1, nA2 : STD_LOGIC;
    signal x0, x1, x2    : STD_LOGIC;

    signal gt2, gt1, gt0 : STD_LOGIC;
    signal lt2, lt1, lt0 : STD_LOGIC;

begin

    -- Inverters
    nA2 <= not A(2);
    nA1 <= not A(1);
    nA0 <= not A(0);
    nB2 <= not B(2);
    nB1 <= not B(1);
    nB0 <= not B(0);

    -- XNORs (bit equality)
    x2 <= not (A(2) xor B(2));
    x1 <= not (A(1) xor B(1));
    x0 <= not (A(0) xor B(0));

    -- Greater-than logic
    gt2 <= A(2) and nB2;
    gt1 <= x2 and A(1) and nB1;
    gt0 <= x2 and x1 and A(0) and nB0;

    GT <= gt2 or gt1 or gt0;

    -- Less-than logic
    lt2 <= nA2 and B(2);
    lt1 <= x2 and nA1 and B(1);
    lt0 <= x2 and x1 and nA0 and B(0);

    LT <= lt2 or lt1 or lt0;

    -- Equality
    EQ <= x2 and x1 and x0;

end structural;

some_vhdl_problems/structural_3bit_comparator/tb_comparator_3bit.vhd
library IEEE;
use IEEE.STD_LOGIC_1164.ALL;

entity tb_comparator_3bit is
end tb_comparator_3bit;

architecture tb of tb_comparator_3bit is

    -- DUT signals
    signal A  : STD_LOGIC_VECTOR(2 downto 0);
    signal B  : STD_LOGIC_VECTOR(2 downto 0);
    signal GT : STD_LOGIC;
    signal EQ : STD_LOGIC;
    signal LT : STD_LOGIC;

begin

    -- Device Under Test
    DUT : entity work.comparator_3bit
        port map (
            A  => A,
            B  => B,
            GT => GT,
            EQ => EQ,
            LT => LT
        );

    -- Stimulus process
    stim_proc : process
    begin

        -- Equal cases
        A <= "000"; B <= "000"; wait for 10 ns;
        A <= "011"; B <= "011"; wait for 10 ns;
        A <= "111"; B <= "111"; wait for 10 ns;

        -- A > B cases
        A <= "001"; B <= "000"; wait for 10 ns;
        A <= "100"; B <= "011"; wait for 10 ns;
        A <= "111"; B <= "110"; wait for 10 ns;

        -- A < B cases
        A <= "000"; B <= "001"; wait for 10 ns;
        A <= "010"; B <= "101"; wait for 10 ns;
        A <= "110"; B <= "111"; wait for 10 ns;

        -- Hold last value
        wait;
    end process;

end tb;

some_vhdl_problems/structural_3bit_comparator/wave.vcd
$date
  Sat Jan 31 06:49:12 2026
$end
$version
  GHDL v0
$end
$timescale
  1 fs
$end
$scope module standard $end
$upscope $end
$scope module std_logic_1164 $end
$upscope $end
$scope module tb_comparator_3bit $end
$var reg 3 ! a[2:0] $end
$var reg 3 " b[2:0] $end
$var reg 1 # gt $end
$var reg 1 $ eq $end
$var reg 1 % lt $end
$scope module dut $end
$var reg 3 & a[2:0] $end
$var reg 3 ' b[2:0] $end
$var reg 1 ( gt $end
$var reg 1 ) eq $end
$var reg 1 * lt $end
$var reg 1 + nb0 $end
$var reg 1 , nb1 $end
$var reg 1 - nb2 $end
$var reg 1 . na0 $end
$var reg 1 / na1 $end
$var reg 1 0 na2 $end
$var reg 1 1 x0 $end
$var reg 1 2 x1 $end
$var reg 1 3 x2 $end
$var reg 1 4 gt2 $end
$var reg 1 5 gt1 $end
$var reg 1 6 gt0 $end
$var reg 1 7 lt2 $end
$var reg 1 8 lt1 $end
$var reg 1 9 lt0 $end
$upscope $end
$upscope $end
$enddefinitions $end
#0
b000 !
b000 "
0#
1$
0%
b000 &
b000 '
0(
1)
0*
1+
1,
1-
1.
1/
10
11
12
13
04
05
06
07
08
09
#10000000
b011 !
b011 "
0#
0%
b011 &
b011 '
0(
0*
0+
0,
0.
0/
05
06
08
09
#20000000
b111 !
b111 "
0#
0%
b111 &
b111 '
0(
0*
0-
00
04
07
#30000000
b001 !
b000 "
1#
0$
b001 &
b000 '
1(
0)
1+
1,
1-
1/
10
01
16
#40000000
b100 !
b011 "
0%
b100 &
b011 '
0*
0+
0,
1.
00
02
03
14
06
08
#50000000
b111 !
b110 "
b111 &
b110 '
1+
0-
0.
0/
12
13
04
16
#60000000
b000 !
b001 "
0#
1%
b000 &
b001 '
0(
1*
0+
1,
1-
1.
1/
10
06
19
#70000000
b010 !
b101 "
0#
b010 &
b101 '
0(
0-
0/
02
03
05
17
09
#80000000
b110 !
b111 "
b110 &
b111 '
0,
00
12
13
07
19
