jk_flipflop/jk_flipflop.vhd
library ieee;
use ieee.std_logic_1164.all;

entity jk_flipflop is
    port(
        clk,j,k : in std_logic;
        q : out std_logic
    );
end entity;

architecture beh of jk_flipflop is
    signal q_prev : std_logic;
begin
    process(clk)
    begin
        if rising_edge(clk) then
            if j = '0' and k = '0' then
                q_prev <= q_prev;
            elsif j = '0' and k = '1' then
                q_prev <= '0';
            elsif j = '1' and k = '0' then
                q_prev <= '1';
            elsif j = '1' and k = '1' then
                q_prev <= not q_prev;
            end if;
        end if;
    end process;
    q <= q_prev;
end architecture;

jk_flipflop/tb_jk_flipflop.vhd
library ieee;
use ieee.std_logic_1164.all;

entity tb_jk_flipflop is
end entity;

architecture beh of tb_jk_flipflop is
    signal j,k,clk,q : std_logic;
    constant clk_period :time := 10 ns;
begin
    uut: entity work.jk_flipflop
        port map(
            j => j,
            k => k,
            clk => clk,
            q => q
        );
    
    process
    begin
        while true loop
            clk <= '0';
            wait for clk_period;
            clk <= '1';
            wait for clk_period;
        end loop;
    end process;

    process
    begin
        j <= '0'; k <= '1'; wait for 20 ns;
        j <= '0'; k <= '0'; wait for 20 ns;
        j <= '1'; k <= '0'; wait for 20 ns;
        j <= '1'; k <= '1'; wait for 20 ns;
        wait;
    end process;
end architecture;

jk_flipflop/wave.vcd
$date
  Sun Dec 14 11:29:12 2025
$end
$version
  GHDL v0
$end
$timescale
  1 fs
$end
$scope module standard $end
$upscope $end
$scope module std_logic_1164 $end
$upscope $end
$scope module tb_jk_flipflop $end
$var reg 1 ! j $end
$var reg 1 " k $end
$var reg 1 # clk $end
$var reg 1 $ q $end
$scope module uut $end
$var reg 1 % clk $end
$var reg 1 & j $end
$var reg 1 ' k $end
$var reg 1 ( q $end
$var reg 1 ) q_prev $end
$upscope $end
$upscope $end
$enddefinitions $end
#0
0!
1"
0#
U$
0%
0&
1'
U(
U)
#10000000
1#
0$
1%
0(
0)
#20000000
0"
0#
0%
0'
#30000000
1#
1%
#40000000
1!
0#
0%
1&
#50000000
1#
1$
1%
1(
1)
#60000000
1"
0#
0%
1'
#70000000
1#
0$
1%
0(
0)
#80000000
0#
0%
#90000000
1#
1$
1%
1(
1)
#100000000
0#
0%
#110000000
1#
0$
1%
0(
0)
#120000000
0#
0%
#130000000
1#
1$
1%
1(
1)
#140000000
0#
0%
#150000000
1#
0$
1%
0(
0)
#160000000
0#
0%
#170000000
1#
1$
1%
1(
1)
#180000000
0#
0%
#190000000
1#
0$
1%
0(
0)
