full_adder/full_adder.vhd
library ieee;
use ieee.std_logic_1164.all;

entity full_adder is
    port(
        a,b,cin : in std_logic;
        s,c : out std_logic
    );
end entity;

architecture beh of full_adder is
begin
    s <= (a xor b) xor cin;
    c <= (a and b) or ((a xor b) and cin);
end architecture;

full_adder/tb_full_adder.vhd
library ieee;
use ieee.std_logic_1164.all;

entity tb_full_adder is
end entity;

architecture sim of tb_full_adder is
  signal a, b, cin, s, c : std_logic;
begin
  -- Instantiate the DUT
  uut: entity work.full_adder
    port map (
      a => a,
      b => b,
      cin => cin,
      s => s,
      c => c
    );

  -- Stimulus process
  process
  begin
    cin <= '0'; a <= '0'; b <= '0'; wait for 100 fs;
    cin <= '0'; a <= '0'; b <= '1'; wait for 100 fs;
    cin <= '0'; a <= '1'; b <= '0'; wait for 100 fs;
    cin <= '0'; a <= '1'; b <= '1'; wait for 100 fs;
    cin <= '1'; a <= '0'; b <= '0'; wait for 100 fs;
    cin <= '1'; a <= '0'; b <= '1'; wait for 100 fs;
    cin <= '1'; a <= '1'; b <= '0'; wait for 100 fs;
    cin <= '1'; a <= '1'; b <= '1'; wait for 100 fs;
    wait;  -- stop simulation
  end process;
end architecture;

full_adder/wave.vcd
$date
  Thu Dec 11 13:20:31 2025
$end
$version
  GHDL v0
$end
$timescale
  1 fs
$end
$scope module standard $end
$upscope $end
$scope module std_logic_1164 $end
$upscope $end
$scope module tb_full_adder $end
$var reg 1 ! a $end
$var reg 1 " b $end
$var reg 1 # cin $end
$var reg 1 $ s $end
$var reg 1 % c $end
$scope module uut $end
$var reg 1 & a $end
$var reg 1 ' b $end
$var reg 1 ( cin $end
$var reg 1 ) s $end
$var reg 1 * c $end
$upscope $end
$upscope $end
$enddefinitions $end
#0
0!
0"
0#
0$
0%
0&
0'
0(
0)
0*
#100
1"
1$
1'
1)
#200
1!
0"
1&
0'
#300
1"
0$
1%
1'
0)
1*
#400
0!
0"
1#
1$
0%
0&
0'
1(
1)
0*
#500
1"
0$
1%
1'
0)
1*
#600
1!
0"
1&
0'
#700
1"
1$
1'
1)
