some_vhdl_problems/universal_shift_register/universal_shift_register_4bit.vhd
library IEEE;
use IEEE.STD_LOGIC_1164.ALL;

entity universal_shift_register_4bit is
    Port (
        clk        : in  STD_LOGIC;
        reset      : in  STD_LOGIC;
        S     : in  STD_LOGIC_VECTOR(1 downto 0);
        serial_in : in  STD_LOGIC; 
        P          : in  STD_LOGIC_VECTOR(3 downto 0); -- parallel input
        Q          : out STD_LOGIC_VECTOR(3 downto 0)
    );
end universal_shift_register_4bit;

architecture behavioral of universal_shift_register_4bit is
    signal reg : STD_LOGIC_VECTOR(3 downto 0);
begin

    process(clk, reset)
    begin
        if reset = '1' then
            reg <= (others => '0');

        elsif rising_edge(clk) then
            case (s) is

                when "00" =>       -- Hold
                    reg <= reg;

                when "01" =>       -- Shift Right
                    reg <= serial_in & reg(3 downto 1);

                when "10" =>       -- Shift Left
                    reg <= reg(2 downto 0) & serial_in;

                when "11" =>       -- Parallel Load
                    reg <= P;

                when others =>
                    reg <= reg;

            end case;
        end if;
    end process;

    Q <= reg;

end behavioral;

some_vhdl_problems/universal_shift_register/tb_universal_shift_register_4bit.vhd
library IEEE;
use IEEE.STD_LOGIC_1164.ALL;

entity tb_universal_shift_register_4bit is
end tb_universal_shift_register_4bit;

architecture behavior of tb_universal_shift_register_4bit is

    -- DUT signals
    signal clk       : STD_LOGIC := '0';
    signal reset     : STD_LOGIC := '0';
    signal S    : STD_LOGIC_VECTOR(1 downto 0);
    signal serial_in : STD_LOGIC;
    signal P         : STD_LOGIC_VECTOR(3 downto 0);
    signal Q         : STD_LOGIC_VECTOR(3 downto 0);

    constant clk_period : time := 10 ns;

begin

    -- ===============================
    -- DUT instantiation (work.entity)
    -- ===============================
    DUT : entity work.universal_shift_register_4bit
        port map (
            clk       => clk,
            reset     => reset,
            S        => S,
            serial_in => serial_in,
            P         => P,
            Q         => Q
        );

    -- ===============================
    -- Clock generation
    -- ===============================
    clk_process : process
    begin
        while true loop
            clk <= '0';
            wait for clk_period / 2;
            clk <= '1';
            wait for clk_period / 2;
        end loop;
    end process;

    -- ===============================
    -- Stimulus process
    -- ===============================
    stim_proc : process
    begin
        -- Reset
        reset <= '1';
        S <= "00";
        
        serial_in <= '0';
        P <= "0000";
        wait for clk_period;

        reset <= '0';
        wait for clk_period;

        -- Parallel load: load 1011
        S <= "11";
        P  <= "1011";
        wait for clk_period;

        -- Hold
        S <= "00";
        wait for clk_period;

        -- Shift right (insert 0)
        S <= "01";
        serial_in <= '0';
        wait for clk_period;

        -- Shift right (insert 1)
        serial_in <= '1';
        wait for clk_period;

        -- Shift left (insert 1)
        S <= "10";
        serial_in <= '1';
        wait for clk_period;

        -- Shift left (insert 0)
        serial_in <= '0';
        wait for clk_period;

        -- End simulation
        wait;
    end process;

end behavior;

some_vhdl_problems/universal_shift_register/wave.vcd
$date
  Sat Jan 31 06:23:17 2026
$end
$version
  GHDL v0
$end
$timescale
  1 fs
$end
$scope module standard $end
$upscope $end
$scope module std_logic_1164 $end
$upscope $end
$scope module tb_universal_shift_register_4bit $end
$var reg 1 ! clk $end
$var reg 1 " reset $end
$var reg 2 # s[1:0] $end
$var reg 1 $ serial_in $end
$var reg 4 % p[3:0] $end
$var reg 4 & q[3:0] $end
$scope module dut $end
$var reg 1 ' clk $end
$var reg 1 ( reset $end
$var reg 2 ) s[1:0] $end
$var reg 1 * serial_in $end
$var reg 4 + p[3:0] $end
$var reg 4 , q[3:0] $end
$var reg 4 - reg[3:0] $end
$upscope $end
$upscope $end
$enddefinitions $end
#0
0!
1"
b00 #
0$
b0000 %
b0000 &
0'
1(
b00 )
0*
b0000 +
b0000 ,
b0000 -
#5000000
1!
1'
#10000000
0!
0"
0'
0(
#15000000
1!
1'
#20000000
0!
b11 #
b1011 %
0'
b11 )
b1011 +
#25000000
1!
b1011 &
1'
b1011 ,
b1011 -
#30000000
0!
b00 #
0'
b00 )
#35000000
1!
1'
#40000000
0!
b01 #
0'
b01 )
#45000000
1!
b0101 &
1'
b0101 ,
b0101 -
#50000000
0!
1$
0'
1*
#55000000
1!
b1010 &
1'
b1010 ,
b1010 -
#60000000
0!
b10 #
0'
b10 )
#65000000
1!
b0101 &
1'
b0101 ,
b0101 -
#70000000
0!
0$
0'
0*
#75000000
1!
b1010 &
1'
b1010 ,
b1010 -
#80000000
0!
0'
#85000000
1!
b0100 &
1'
b0100 ,
b0100 -
#90000000
0!
0'
#95000000
1!
b1000 &
1'
b1000 ,
b1000 -
#100000000
0!
0'
#105000000
1!
b0000 &
1'
b0000 ,
b0000 -
